purewebm/__init__.py
purewebm/__main__.py
purewebm/config.py
purewebm/console.py
purewebm/encoder.py
purewebm/ffmpeg.py
purewebm/ipc.py
purewebm/video.py
purewebm-1.2.1.dist-info/METADATA
purewebm-1.2.1.dist-info/WHEEL
purewebm-1.2.1.dist-info/entry_points.txt
purewebm-1.2.1.dist-info/licenses/LICENSE
purewebm-1.2.1.dist-info/RECORD
