Metadata-Version: 2.1
Name: purewebm
Version: 1.2.1
Summary: Wrapper around ffmpeg to encode quick size restricted webms
Project-URL: Homepage, https://github.com/4ndrs/PureWebM
Project-URL: Bug Tracker, https://github.com/4ndrs/PureWebM/issues
Author-email: 4ndrs <andres.degozaru@gmail.com>
License: MIT License
License-File: LICENSE
Classifier: License :: OSI Approved :: MIT License
Classifier: Operating System :: POSIX :: Linux
Classifier: Programming Language :: Python :: 3
Requires-Python: >=3.8
